django_request_track-0.8.2.dist-info/licenses/LICENSE
request_track/__init__.py
request_track/admin.py
request_track/apps.py
request_track/middleware.py
request_track/models.py
request_track/settings.py
request_track/tasks.py
request_track/utils.py
request_track/migrations/0001_initial.py
request_track/migrations/__init__.py
request_track/templates/request_track/admin/requestlog_change_list.html
request_track/templates/request_track/admin/requestlog_maintenance.html
request_track/tests/__init__.py
request_track/tests/test_admin.py
request_track/tests/test_integration.py
request_track/tests/test_middleware.py
request_track/tests/test_model.py
request_track/tests/test_tasks.py
request_track/tests/test_utils.py
django_request_track-0.8.2.dist-info/METADATA
django_request_track-0.8.2.dist-info/WHEEL
django_request_track-0.8.2.dist-info/top_level.txt
django_request_track-0.8.2.dist-info/RECORD
