Metadata-Version: 2.4
Name: django-request-track
Version: 0.8.2
Summary: A Django package to track requests with optional Redis and Celery support.
Author-email: PooyaRezaee <pooya.rezaee.official@gmail.com>
License: MIT
Project-URL: Homepage, https://github.com/PooyaRezaee/django-request-track
Project-URL: Repository, https://github.com/PooyaRezaee/django-request-track
Keywords: django,middleware,request,logging,redis,celery
Classifier: Framework :: Django
Classifier: Programming Language :: Python :: 3
Classifier: License :: OSI Approved :: MIT License
Classifier: Operating System :: OS Independent
Requires-Python: >=3.8
License-File: LICENSE
Requires-Dist: Django>=5.0.0
Requires-Dist: redis
Requires-Dist: celery
Requires-Dist: msgpack
Provides-Extra: dev
Requires-Dist: pytest; extra == "dev"
Requires-Dist: tox; extra == "dev"
Requires-Dist: flake8; extra == "dev"
Dynamic: license-file
